repoze.filesafe-2.2-py3.4-nspkg.pth
repoze/filesafe/__init__.py
repoze/filesafe/manager.py
repoze/filesafe/testing.py
repoze/filesafe/tests.py
repoze.filesafe-2.2.dist-info/DESCRIPTION.rst
repoze.filesafe-2.2.dist-info/entry_points.txt
repoze.filesafe-2.2.dist-info/METADATA
repoze.filesafe-2.2.dist-info/metadata.json
repoze.filesafe-2.2.dist-info/namespace_packages.txt
repoze.filesafe-2.2.dist-info/RECORD
repoze.filesafe-2.2.dist-info/top_level.txt
repoze.filesafe-2.2.dist-info/WHEEL
